ALUpdation/__init__.py
ALUpdation/classifierhelper.py
ALUpdation/datasetup.py
ALUpdation/uncertaintylearner.py
AL_for_design/__init__.py
AL_for_design/bayesian_learner.py
AL_for_design/classifier_learner.py
AL_for_design/datasetup.py
AL_for_design/helper.py
AL_for_design/hyperparameter_learner.py
AL_for_design/quantized_learner.py
AL_for_design/regressor_learner.py
AL_for_design/simplified_learner.py
al_for_design-0.0.1.dist-info/LICENSE
al_for_design-0.0.1.dist-info/METADATA
al_for_design-0.0.1.dist-info/WHEEL
al_for_design-0.0.1.dist-info/top_level.txt
al_for_design-0.0.1.dist-info/RECORD
