Metadata-Version: 2.1
Name: al-for-design
Version: 0.0.1
Summary: A library for optimally generating data with batch active learning in design contexts
Author: Advaith Narayanan
Author-email: advaith.narayanan20@gmail.com
License: MIT
Classifier: Development Status :: 3 - Alpha
Classifier: License :: OSI Approved :: MIT License
Classifier: Programming Language :: Python :: 3
Requires-Python: >=3.6
License-File: LICENSE
Requires-Dist: numpy
Requires-Dist: pandas
Requires-Dist: tensorflow
Requires-Dist: scikit-learn
Requires-Dist: matplotlib
Requires-Dist: sobol-seq
Requires-Dist: autogluon
Requires-Dist: Pillow (==6.2.1)
